{
  "slug": "georgia",
  "name": "Georgia",
  "continent": "europe",
  "continentName": "Europe",
  "depth": 4,
  "seo": {
    "title": "Sports Events in Georgia 2026",
    "description": "Georgia historical timeline, capital, population, events and travel context.",
    "twitterDescription": "Find sports events in Georgia in 2026: calendars, nearby pages and linked event views for planning around Europe / Georgia.",
    "webpageDescription": "Find sports events in Georgia in 2026: calendars, nearby pages and linked event views for planning around Europe / Georgia."
  },
  "kpis": {
    "capital": "Tbilisi",
    "capitalLink": "tbilisi.html",
    "population": "4M",
    "area": "69,700 km2",
    "currency": "lari"
  },
  "history": [
    {
      "time": "337",
      "text": "Christianity became established as the state religion of ancient Iberia."
    },
    {
      "time": "1008",
      "text": "The unified Kingdom of Georgia emerged ruled or strongly influenced the territory before the modern state."
    },
    {
      "time": "1801",
      "text": "The Russian Empire annexed eastern Georgia ruled or strongly influenced the territory before the modern state."
    },
    {
      "time": "1918",
      "text": "Georgia declared independence as the Democratic Republic of Georgia."
    },
    {
      "time": "1991",
      "text": "Georgia restored independence from the Soviet Union."
    }
  ],
  "shortFacts": [
    {
      "label": "Region",
      "value": "South Caucasus"
    },
    {
      "label": "Language",
      "value": "Georgian"
    },
    {
      "label": "Time zone",
      "value": "GET (UTC+4)"
    },
    {
      "label": "Drives on",
      "value": "Right"
    }
  ],
  "worthSeeing": [
    {
      "title": "Kazbegi Mountains:",
      "text": "Gergeti Trinity Church perched at 2,170 m with views of Mount Kazbegi."
    },
    {
      "title": "Wine Cradle:",
      "text": "The 8,000-year-old tradition of fermenting wine in clay qvevri pots."
    },
    {
      "title": "Tbilisi Old Town:",
      "text": "Balconied wooden houses, sulphur baths and eclectic architecture in the capital."
    }
  ],
  "cities": [
    {
      "name": "Tbilisi",
      "href": "tbilisi.html",
      "img": "/content/locations/europe/georgia/img/tbilisi-mini.png"
    }
  ],
  "links": [
    {
      "kind": "Browse",
      "label": "More locations",
      "href": "../../../locations/index.html"
    },
    {
      "kind": "Topics",
      "label": "Travel interests",
      "href": "../../../categories/index.html"
    }
  ],
  "planningQuestions": [
    {
      "q": "What is Georgia known for?",
      "a": "Kazbegi Mountains, Wine Cradle, Tbilisi Old Town."
    },
    {
      "q": "What is the capital?",
      "a": "Tbilisi."
    },
    {
      "q": "Which language is useful?",
      "a": "Georgian."
    },
    {
      "q": "When is the national day?",
      "a": "26 May."
    }
  ],
  "events": [
    {
      "modifier": "national",
      "dataEnd": "2026-05-26",
      "href": "/content/categories/culture/national-day/events/georgia-independence-day.html",
      "img": "/content/categories/culture/national-day/events/img/georgia-independence-day-mini.png",
      "title": "Georgia Independence Day",
      "meta": "26 May 2026 · Georgia"
    }
  ],
  "eventsEmptyText": "No future Georgia-linked events are active in the current dataset.",
  "food": [
    {
      "href": "../../../categories/food/khachapuri.html",
      "img": "/content/categories/food/img/khachapuri-mini.png",
      "title": "Khachapuri",
      "label": "Signature dish"
    },
    {
      "href": "../../../categories/drinks/wine.html",
      "img": "/content/categories/drinks/img/wine-mini.png",
      "title": "Wine",
      "label": "Local drink"
    }
  ],
  "knownFor": [
    "Kazbegi Mountains",
    "170 m",
    "Wine Cradle",
    "The 8",
    "Tbilisi Old Town",
    "sulphur baths"
  ],
  "topicCards": [
    {
      "modifier": "alpine",
      "href": "../../../categories/sport/alpine-skiing.html",
      "img": "/content/categories/sport/multi-sport/events/img/winter-olympics-mini.png",
      "alt": "Winter Olympics 2030",
      "title": "Alpine Skiing",
      "text": "Mountain venues, races and winter calendars."
    }
  ]
}