{
  "slug": "france",
  "name": "France",
  "continent": "europe",
  "continentName": "Europe",
  "depth": 4,
  "seo": {
    "title": "Sports Events in France 2026",
    "description": "France historical timeline, capital, population, events and travel context.",
    "twitterDescription": "Find sports events in France in 2026: calendars, nearby pages and linked event views for planning around Europe / France.",
    "webpageDescription": "Find sports events in France in 2026: calendars, nearby pages and linked event views for planning around Europe / France."
  },
  "kpis": {
    "capital": "Paris",
    "capitalLink": "paris.html",
    "population": "66.4M",
    "area": "551,695 km2",
    "currency": "euro"
  },
  "history": [
    {
      "time": "843",
      "text": "The Treaty of Verdun divided the Carolingian Empire and shaped West Francia."
    },
    {
      "time": "987",
      "text": "Hugh Capet became king, beginning the Capetian dynasty."
    },
    {
      "time": "1789",
      "text": "The French Revolution began reshaped France's political life."
    },
    {
      "time": "1958",
      "text": "The Fifth Republic was founded introduced a new form of state rule."
    },
    {
      "time": "1993",
      "text": "France became part of the European Union through the Maastricht Treaty."
    }
  ],
  "shortFacts": [
    {
      "label": "Region",
      "value": "Western Europe"
    },
    {
      "label": "Language",
      "value": "French"
    },
    {
      "label": "Time zone",
      "value": "CET (UTC+1)"
    },
    {
      "label": "Drives on",
      "value": "Right"
    }
  ],
  "worthSeeing": [
    {
      "title": "Paris:",
      "text": "The Eiffel Tower, Louvre and Notre-Dame draw more visitors than anywhere on Earth."
    },
    {
      "title": "Gastronomy:",
      "text": "French cuisine is UNESCO-listed heritage with Michelin-starred restaurants in every region."
    },
    {
      "title": "Cote d Azur:",
      "text": "The French Riviera combines glamour, beaches and hilltop villages."
    }
  ],
  "cities": [
    {
      "name": "Cannes",
      "href": "cannes.html",
      "img": "/content/locations/europe/france/img/cannes-mini.png"
    },
    {
      "name": "Paris",
      "href": "paris.html",
      "img": "/content/locations/europe/france/img/paris-mini.png"
    }
  ],
  "links": [
    {
      "kind": "Browse",
      "label": "More locations",
      "href": "../../../locations/index.html"
    },
    {
      "kind": "Topics",
      "label": "Travel interests",
      "href": "../../../categories/index.html"
    }
  ],
  "planningQuestions": [
    {
      "q": "What is France known for?",
      "a": "Paris, Gastronomy, Cote d Azur."
    },
    {
      "q": "What is the capital?",
      "a": "Paris."
    },
    {
      "q": "Which language is useful?",
      "a": "French."
    },
    {
      "q": "When is the national day?",
      "a": "14 July."
    },
    {
      "q": "How should I browse it here?",
      "a": "Start with the facts, jump to linked cities, then check events and topics."
    }
  ],
  "events": [
    {
      "modifier": "national",
      "dataEnd": "2026-07-12",
      "href": "/content/categories/sport/golf/events/amundi-evian-championship.html",
      "img": "/content/categories/sport/golf/events/img/amundi-evian-championship-mini.png",
      "title": "Amundi Evian Championship",
      "meta": "2026-07-09 - 2026-07-12 - LPGA Tour"
    },
    {
      "modifier": "national",
      "dataEnd": "2026-07-14",
      "href": "/content/categories/culture/national-day/events/bastille-day.html",
      "img": "/content/categories/culture/national-day/events/img/bastille-day-mini.png",
      "title": "Bastille Day",
      "meta": "14 Jul 2026 · France"
    },
    {
      "modifier": "national",
      "dataEnd": "2026-06-07",
      "href": "/content/categories/sport/tennis/events/roland-garros.html",
      "img": "/content/categories/sport/tennis/events/img/roland-garros-mini.png",
      "title": "French Open / Roland Garros",
      "meta": "24 May - 7 Jun 2026 · Paris, France"
    },
    {
      "modifier": "national",
      "dataEnd": "2026-06-14",
      "href": "/content/categories/sport/motorsport/events/le-mans-24-hours.html",
      "img": "/content/categories/sport/motorsport/events/img/le-mans-24-hours-mini.png",
      "title": "Le Mans 24 Hours",
      "meta": "13-14 Jun 2026 · Le Mans, France"
    },
    {
      "modifier": "national",
      "dataEnd": "2026-07-26",
      "href": "/content/categories/sport/cycling/events/tour-de-france.html",
      "img": "/content/categories/sport/cycling/events/img/tour-de-france-mini.png",
      "title": "Tour de France",
      "meta": "27 Jun - 26 Jul 2026 ·"
    },
    {
      "modifier": "national",
      "dataEnd": "2030-02-17",
      "href": "/content/categories/sport/multi-sport/events/winter-olympics.html",
      "img": "/content/categories/sport/multi-sport/events/img/winter-olympics-mini.png",
      "title": "Winter Olympics 2030",
      "meta": "1-17 Feb 2030 · French Alps, France"
    }
  ],
  "eventsEmptyText": "No future France-linked events are active in the current dataset.",
  "food": [
    {
      "href": "../../../categories/food/baguette.html",
      "img": "/content/categories/food/img/baguette-mini.png",
      "title": "Baguette",
      "label": "Signature dish"
    },
    {
      "href": "../../../categories/drinks/wine.html",
      "img": "/content/categories/drinks/img/wine-mini.png",
      "title": "Wine",
      "label": "Local drink"
    }
  ],
  "knownFor": [
    "Paris",
    "The Eiffel Tower",
    "Louvre",
    "Gastronomy",
    "Cote d Azur",
    "beaches",
    "hilltop villages."
  ],
  "topicCards": [
    {
      "modifier": "music",
      "href": "../../../categories/music/index.html",
      "img": "/content/categories/music/song-contests/events/img/eurovision-song-contest-mini.png",
      "alt": "Eurovision Song Contest",
      "title": "Music & Culture",
      "text": "Festivals, concerts and cultural calendars."
    },
    {
      "modifier": "national",
      "href": "../../../categories/nature/index.html",
      "img": "/content/categories/img/categories-topics-mini.png",
      "alt": "Categories Topics",
      "title": "Nature & places",
      "text": "Landscapes, routes, coastlines and outdoor context."
    }
  ]
}